xsdata/__init__.py
xsdata/__main__.py
xsdata/cli.py
xsdata/exceptions.py
xsdata/logger.py
xsdata/py.typed
xsdata/codegen/__init__.py
xsdata/codegen/container.py
xsdata/codegen/exceptions.py
xsdata/codegen/mixins.py
xsdata/codegen/models.py
xsdata/codegen/resolver.py
xsdata/codegen/stopwatch.py
xsdata/codegen/transformer.py
xsdata/codegen/utils.py
xsdata/codegen/validator.py
xsdata/codegen/writer.py
xsdata/codegen/handlers/__init__.py
xsdata/codegen/handlers/add_attribute_substitutions.py
xsdata/codegen/handlers/calculate_attribute_paths.py
xsdata/codegen/handlers/create_compound_fields.py
xsdata/codegen/handlers/create_wrapper_fields.py
xsdata/codegen/handlers/designate_class_packages.py
xsdata/codegen/handlers/detect_circular_references.py
xsdata/codegen/handlers/disambiguate_choices.py
xsdata/codegen/handlers/filter_classes.py
xsdata/codegen/handlers/flatten_attribute_groups.py
xsdata/codegen/handlers/flatten_class_extensions.py
xsdata/codegen/handlers/merge_attributes.py
xsdata/codegen/handlers/process_attributes_types.py
xsdata/codegen/handlers/process_mixed_content_class.py
xsdata/codegen/handlers/rename_duplicate_attributes.py
xsdata/codegen/handlers/rename_duplicate_classes.py
xsdata/codegen/handlers/reset_attribute_sequence_numbers.py
xsdata/codegen/handlers/reset_attribute_sequences.py
xsdata/codegen/handlers/sanitize_attributes_default_value.py
xsdata/codegen/handlers/sanitize_enumeration_class.py
xsdata/codegen/handlers/unnest_inner_classes.py
xsdata/codegen/handlers/update_attributes_effective_choice.py
xsdata/codegen/handlers/vacuum_inner_classes.py
xsdata/codegen/handlers/validate_attributes_overrides.py
xsdata/codegen/handlers/validate_references.py
xsdata/codegen/mappers/__init__.py
xsdata/codegen/mappers/definitions.py
xsdata/codegen/mappers/dict.py
xsdata/codegen/mappers/dtd.py
xsdata/codegen/mappers/element.py
xsdata/codegen/mappers/mixins.py
xsdata/codegen/mappers/schema.py
xsdata/codegen/parsers/__init__.py
xsdata/codegen/parsers/definitions.py
xsdata-24.12.dist-info/LICENSE
xsdata-24.12.dist-info/METADATA
xsdata-24.12.dist-info/WHEEL
xsdata-24.12.dist-info/entry_points.txt
xsdata-24.12.dist-info/top_level.txt
xsdata-24.12.dist-info/RECORD
